{
	"configurations" : 
	[
		{
			"directories" : 
			[
				{
					"build" : ".",
					"jsonFile" : "directory-.-RelWithDebInfo-f5ebdc15457944623624.json",
					"minimumCMakeVersion" : 
					{
						"string" : "3.6.0"
					},
					"projectIndex" : 0,
					"source" : ".",
					"targetIndexes" : 
					[
						0
					]
				}
			],
			"name" : "RelWithDebInfo",
			"projects" : 
			[
				{
					"directoryIndexes" : 
					[
						0
					],
					"name" : "pikafish",
					"targetIndexes" : 
					[
						0
					]
				}
			],
			"targets" : 
			[
				{
					"directoryIndex" : 0,
					"id" : "pikafish::@6890427a1f51a3e7e1df",
					"jsonFile" : "target-pikafish-RelWithDebInfo-44f19d3d41c1edd0f52e.json",
					"name" : "pikafish",
					"projectIndex" : 0
				}
			]
		}
	],
	"kind" : "codemodel",
	"paths" : 
	{
		"build" : "/Users/trangiang/Desktop/game/rose_flutter/android/app/.cxx/RelWithDebInfo/3s565wrn/arm64-v8a",
		"source" : "/Users/trangiang/Desktop/game/rose_flutter/android/app"
	},
	"version" : 
	{
		"major" : 2,
		"minor" : 3
	}
}
